warreclient/__init__.py
warreclient/client.py
warreclient/osc/__init__.py
warreclient/osc/plugin.py
warreclient/osc/v1/__init__.py
warreclient/osc/v1/flavors.py
warreclient/osc/v1/limits.py
warreclient/osc/v1/reservations.py
warreclient/tests/__init__.py
warreclient/tests/unit/__init__.py
warreclient/tests/unit/v1/__init__.py
warreclient/tests/unit/v1/fakes.py
warreclient/tests/unit/v1/test_flavorprojects.py
warreclient/tests/unit/v1/test_flavors.py
warreclient/tests/unit/v1/test_limits.py
warreclient/tests/unit/v1/test_reservations.py
warreclient/v1/__init__.py
warreclient/v1/client.py
warreclient/v1/flavorprojects.py
warreclient/v1/flavors.py
warreclient/v1/limits.py
warreclient/v1/reservations.py
warreclient-3.1.2.dist-info/licenses/LICENSE
warreclient-3.1.2.dist-info/METADATA
warreclient-3.1.2.dist-info/WHEEL
warreclient-3.1.2.dist-info/entry_points.txt
warreclient-3.1.2.dist-info/pbr.json
warreclient-3.1.2.dist-info/top_level.txt
warreclient-3.1.2.dist-info/RECORD
